chat2llms/__init__.py
chat2llms/analyzer.py
chat2llms/base_client.py
chat2llms/model_response.py
chat2llms/output_files.py
chat2llms/utils.py
chat2llms-0.1.0.dist-info/licenses/LICENSE
chat2llms-0.1.0.dist-info/METADATA
chat2llms-0.1.0.dist-info/WHEEL
chat2llms-0.1.0.dist-info/entry_points.txt
chat2llms-0.1.0.dist-info/top_level.txt
chat2llms-0.1.0.dist-info/RECORD
